sweetviz/__init__.py
sweetviz/comet_ml_logger.py
sweetviz/config.py
sweetviz/dataframe_report.py
sweetviz/feature_config.py
sweetviz/from_dython.py
sweetviz/from_profiling_pandas.py
sweetviz/graph.py
sweetviz/graph_associations.py
sweetviz/graph_cat.py
sweetviz/graph_legend.py
sweetviz/graph_numeric.py
sweetviz/series_analyzer.py
sweetviz/series_analyzer_cat.py
sweetviz/series_analyzer_numeric.py
sweetviz/series_analyzer_text.py
sweetviz/sv_html.py
sweetviz/sv_html_formatters.py
sweetviz/sv_math.py
sweetviz/sv_public.py
sweetviz/sv_types.py
sweetviz/sweetviz_defaults.ini
sweetviz/type_detection.py
sweetviz/update_jquery.py
sweetviz/utils.py
sweetviz/fonts/LICENSE_OFL.txt
sweetviz/fonts/NotoSansCJK-Medium.ttc
sweetviz/fonts/Roboto-Medium.ttf
sweetviz/mpl_styles/graph_base.mplstyle
sweetviz/mpl_styles/graph_target.mplstyle
sweetviz/templates/dataframe_associations.html
sweetviz/templates/dataframe_page.html
sweetviz/templates/dataframe_summary.html
sweetviz/templates/feature_detail_cat.html
sweetviz/templates/feature_detail_numeric.html
sweetviz/templates/feature_detail_text.html
sweetviz/templates/feature_summary_base_stats.html
sweetviz/templates/feature_summary_cat.html
sweetviz/templates/feature_summary_numeric.html
sweetviz/templates/feature_summary_target_cat.html
sweetviz/templates/feature_summary_target_numeric.html
sweetviz/templates/feature_summary_text.html
sweetviz/templates/include_missing.html
sweetviz/templates/sv_assets.css
sweetviz/templates/sweetviz.css
sweetviz/templates/js/jquery-3.7.1.min.js
sweetviz/templates/js/sweetviz.js
sweetviz/templates/js/sweetviz_vertical.js
sweetviz_cb-2.3.2.dist-info/licenses/LICENSE
sweetviz_cb-2.3.2.dist-info/METADATA
sweetviz_cb-2.3.2.dist-info/WHEEL
sweetviz_cb-2.3.2.dist-info/top_level.txt
sweetviz_cb-2.3.2.dist-info/RECORD
