Metadata-Version: 2.4
Name: sweetviz-cb
Version: 2.3.2
Summary: A pandas-based library to visualize and compare datasets.
Author-email: Francois Bertrand <fb@fbdesignpro.com>
License-Expression: MIT
Project-URL: Homepage, https://github.com/marcelocb/sweetviz-cb
Project-URL: Bug Tracker, https://github.com/marcelocb/sweetviz-cb/issues
Project-URL: Discussions, https://github.com/marcelocb/sweetviz-cb/discussions
Project-URL: Changelog, https://github.com/marcelocb/sweetviz-cb/releases
Keywords: pandas,data-science,data-analysis,python,eda
Classifier: Programming Language :: Python :: 3
Classifier: Programming Language :: Python :: 3.7
Classifier: Programming Language :: Python :: 3.8
Classifier: Programming Language :: Python :: 3.9
Classifier: Programming Language :: Python :: 3.10
Classifier: Programming Language :: Python :: 3.11
Classifier: Programming Language :: Python :: 3.12
Classifier: Programming Language :: Python :: 3.13
Classifier: Intended Audience :: Developers
Classifier: Intended Audience :: Science/Research
Classifier: Operating System :: OS Independent
Classifier: Development Status :: 5 - Production/Stable
Classifier: Topic :: Scientific/Engineering :: Visualization
Classifier: Topic :: Software Development :: Libraries :: Python Modules
Requires-Python: >=3.9
License-File: LICENSE
Requires-Dist: pandas>=2.2
Requires-Dist: numpy>=2.0
Requires-Dist: matplotlib>=3.8
Requires-Dist: tqdm>=4.43.0
Requires-Dist: scipy>=1.3.2
Requires-Dist: jinja2>=3.1
Requires-Dist: importlib_resources>=5; python_version < "3.9"
Requires-Dist: importlib_metadata>=4.6; python_version < "3.8"
Provides-Extra: test
Requires-Dist: pytest>=6; extra == "test"
Requires-Dist: pytest-cov>=3; extra == "test"
Provides-Extra: dev
Requires-Dist: pytest>=6; extra == "dev"
Requires-Dist: pytest-cov>=3; extra == "dev"
Provides-Extra: docs
Requires-Dist: sphinx>=4.0; extra == "docs"
Requires-Dist: myst_parser>=0.13; extra == "docs"
Requires-Dist: sphinx_book_theme>=0.1.0; extra == "docs"
Requires-Dist: sphinx_copybutton; extra == "docs"
Requires-Dist: sphinx_autodoc_typehints; extra == "docs"
Requires-Dist: furo; extra == "docs"
Dynamic: license-file
